LICENSE
README.md
pyproject.toml
src/amltk/__init__.py
src/amltk/__version__.py
src/amltk/_asyncm.py
src/amltk/_doc.py
src/amltk/_functional.py
src/amltk/_util.py
src/amltk/distances.py
src/amltk/exceptions.py
src/amltk/options.py
src/amltk/py.typed
src/amltk/randomness.py
src/amltk/types.py
src/amltk.egg-info/PKG-INFO
src/amltk.egg-info/SOURCES.txt
src/amltk.egg-info/dependency_links.txt
src/amltk.egg-info/requires.txt
src/amltk.egg-info/top_level.txt
src/amltk/_richutil/__init__.py
src/amltk/_richutil/renderable.py
src/amltk/_richutil/util.py
src/amltk/_richutil/renderers/__init__.py
src/amltk/_richutil/renderers/_make_column_selector.py
src/amltk/_richutil/renderers/executors.py
src/amltk/_richutil/renderers/function.py
src/amltk/data/__init__.py
src/amltk/data/conversions.py
src/amltk/data/dtype_reduction.py
src/amltk/data/measure.py
src/amltk/ensembling/__init__.py
src/amltk/ensembling/weighted_ensemble_caruana.py
src/amltk/metalearning/__init__.py
src/amltk/metalearning/dataset_distances.py
src/amltk/metalearning/metafeatures.py
src/amltk/metalearning/portfolio.py
src/amltk/optimization/__init__.py
src/amltk/optimization/evaluation.py
src/amltk/optimization/history.py
src/amltk/optimization/metric.py
src/amltk/optimization/optimizer.py
src/amltk/optimization/trial.py
src/amltk/optimization/optimizers/__init__.py
src/amltk/optimization/optimizers/neps.py
src/amltk/optimization/optimizers/optuna.py
src/amltk/optimization/optimizers/random_search.py
src/amltk/optimization/optimizers/smac.py
src/amltk/pipeline/__init__.py
src/amltk/pipeline/components.py
src/amltk/pipeline/node.py
src/amltk/pipeline/ops.py
src/amltk/pipeline/xgboost.py
src/amltk/pipeline/builders/__init__.py
src/amltk/pipeline/builders/sklearn.py
src/amltk/pipeline/parsers/__init__.py
src/amltk/pipeline/parsers/configspace.py
src/amltk/pipeline/parsers/optuna.py
src/amltk/profiling/__init__.py
src/amltk/profiling/memory.py
src/amltk/profiling/profiler.py
src/amltk/profiling/timing.py
src/amltk/pytorch/__init__.py
src/amltk/pytorch/builders.py
src/amltk/scheduling/__init__.py
src/amltk/scheduling/events.py
src/amltk/scheduling/queue_monitor.py
