Metadata-Version: 2.1
Name: amltk
Version: 1.12.0
Summary: AutoML Toolkit: a toolkit for building automl system
Author-email: Eddie Bergman <eddiebergmanhs@gmail.com>
License: Copyright 2023 AutoML-Freiburg-Hannover-Tübingen
Project-URL: documentation, https://github.com/automl/amltk/
Project-URL: source, https://github.com/automl/amltk/
Classifier: Intended Audience :: Science/Research
Classifier: Intended Audience :: Developers
Classifier: License :: OSI Approved :: BSD License
Classifier: Programming Language :: Python
Classifier: Topic :: Software Development
Classifier: Topic :: Scientific/Engineering
Classifier: Operating System :: POSIX
Classifier: Operating System :: Unix
Classifier: Operating System :: MacOS
Classifier: Programming Language :: Python :: 3
Classifier: Programming Language :: Python :: 3.10
Classifier: Programming Language :: Python :: 3.11
Requires-Python: >=3.10
License-File: LICENSE
Requires-Dist: typing_extensions
Requires-Dist: more_itertools
Requires-Dist: psutil
Requires-Dist: pandas
Requires-Dist: numpy
Provides-Extra: dev
Requires-Dist: amltk[doc,examples,test,tooling]; extra == "dev"
Provides-Extra: tooling
Requires-Dist: commitizen; extra == "tooling"
Requires-Dist: pre-commit; extra == "tooling"
Requires-Dist: ruff; extra == "tooling"
Requires-Dist: mypy; extra == "tooling"
Requires-Dist: types-psutil; extra == "tooling"
Requires-Dist: types-pyyaml; extra == "tooling"
Provides-Extra: test
Requires-Dist: pytest<8; extra == "test"
Requires-Dist: pytest-coverage; extra == "test"
Requires-Dist: pytest-cases; extra == "test"
Requires-Dist: amltk[examples]; extra == "test"
Requires-Dist: torch; extra == "test"
Provides-Extra: examples
Requires-Dist: openml; extra == "examples"
Requires-Dist: amltk[dask,loky,optuna,path_loaders,pynisher,rich,sklearn,smac,wandb,xgboost]; extra == "examples"
Provides-Extra: doc
Requires-Dist: mkdocs; extra == "doc"
Requires-Dist: mkdocs-material; extra == "doc"
Requires-Dist: mkdocs-autorefs; extra == "doc"
Requires-Dist: mkdocs-gen-files; extra == "doc"
Requires-Dist: mkdocs-literate-nav; extra == "doc"
Requires-Dist: mkdocs-glightbox; extra == "doc"
Requires-Dist: mkdocstrings[python]; extra == "doc"
Requires-Dist: markdown-exec[ansi]; extra == "doc"
Requires-Dist: matplotlib; extra == "doc"
Requires-Dist: rich; extra == "doc"
Requires-Dist: mike; extra == "doc"
Requires-Dist: pillow; extra == "doc"
Requires-Dist: cairosvg; extra == "doc"
Requires-Dist: black; extra == "doc"
Provides-Extra: sklearn
Requires-Dist: scikit-learn; extra == "sklearn"
Requires-Dist: threadpoolctl; extra == "sklearn"
Provides-Extra: smac
Requires-Dist: smac>=2.0; extra == "smac"
Requires-Dist: amltk[configspace]; extra == "smac"
Provides-Extra: optuna
Requires-Dist: optuna; extra == "optuna"
Provides-Extra: configspace
Requires-Dist: configspace>=0.6; extra == "configspace"
Provides-Extra: loky
Requires-Dist: loky; extra == "loky"
Provides-Extra: dask
Requires-Dist: dask; extra == "dask"
Requires-Dist: distributed; extra == "dask"
Provides-Extra: pynisher
Requires-Dist: pynisher>=1.0.10; extra == "pynisher"
Provides-Extra: wandb
Requires-Dist: wandb; extra == "wandb"
Provides-Extra: threadpoolctl
Requires-Dist: threadpoolctl; extra == "threadpoolctl"
Provides-Extra: xgboost
Requires-Dist: xgboost; extra == "xgboost"
Provides-Extra: neps
Requires-Dist: neural-pipeline-search; extra == "neps"
Provides-Extra: rich
Requires-Dist: rich; extra == "rich"
Provides-Extra: cluster
Requires-Dist: dask-jobqueue; extra == "cluster"
Provides-Extra: notebook
Requires-Dist: rich[jupyter]; extra == "notebook"
Provides-Extra: path-loaders
Requires-Dist: openpyxl; extra == "path-loaders"
Requires-Dist: pyarrow; extra == "path-loaders"
